cl_bindgen/__init__.py
cl_bindgen/__main__.py
cl_bindgen/mangler.py
cl_bindgen/processfile.py
cl_bindgen/util.py
cl_bindgen-1.2.1.dist-info/LICENSE
cl_bindgen-1.2.1.dist-info/METADATA
cl_bindgen-1.2.1.dist-info/WHEEL
cl_bindgen-1.2.1.dist-info/entry_points.txt
cl_bindgen-1.2.1.dist-info/top_level.txt
cl_bindgen-1.2.1.dist-info/RECORD
