Metadata-Version: 2.1
Name: cl-bindgen
Version: 1.2.1
Summary: A command line tool and library for creating Common Lisp language bindings from C header files
Home-page: https://github.com/sdilts/cl-bindgen
Download-URL: https://github.com/sdilts/cl-bindgen/archive/1.1.3.tar.gz
Author: Stuart Dilts
Author-email: stuart.dilts@gmail.com
License: MIT
Classifier: Intended Audience :: Developers
Classifier: Topic :: Software Development
Classifier: Programming Language :: Python :: 3
License-File: LICENSE
Requires-Dist: clang
Requires-Dist: PyYAML
